funapi/__init__.py
funawesome-0.0.1.dist-info/LICENSE
funawesome-0.0.1.dist-info/METADATA
funawesome-0.0.1.dist-info/WHEEL
funawesome-0.0.1.dist-info/entry_points.txt
funawesome-0.0.1.dist-info/top_level.txt
funawesome-0.0.1.dist-info/RECORD
